nonebot_plugin_aitalk/__init__.py
nonebot_plugin_aitalk/api.py
nonebot_plugin_aitalk/cd.py
nonebot_plugin_aitalk/config.py
nonebot_plugin_aitalk/data.py
nonebot_plugin_aitalk/msg_seg.py
nonebot_plugin_aitalk/utils.py
nonebot_plugin_aitalk-3.13.38.dist-info/LICENSE
nonebot_plugin_aitalk-3.13.38.dist-info/WHEEL
nonebot_plugin_aitalk-3.13.38.dist-info/METADATA
nonebot_plugin_aitalk-3.13.38.dist-info/RECORD
