Metadata-Version: 2.1
Name: nonebot-plugin-aitalk
Version: 3.13.38
Summary: 简单好用的AI聊天插件，支持多API，支持让AI理解图片，发送表情包，合成语音，艾特，戳一戳，禁言/解除禁言等；可配置关键词允许AI主动发言
Home-page: https://github.com/captain-wangrun-cn/nonebot-plugin-aitalk
License: GPL-3.0
Author: WR
Author-email: wangrun114514@foxmail.com
Requires-Python: >=3.9,<4.0
Classifier: License :: OSI Approved :: GNU General Public License v3 (GPLv3)
Classifier: Programming Language :: Python :: 3
Classifier: Programming Language :: Python :: 3.10
Classifier: Programming Language :: Python :: 3.9
Requires-Dist: aiofiles (>=24.1.0,<25.0.0)
Requires-Dist: fish_audio_sdk (==1.0.0)
Requires-Dist: nonebot-adapter-onebot (>=2.0.0,<3.0.0)
Requires-Dist: nonebot-plugin-localstore (>=0.7.3,<0.8.0)
Requires-Dist: nonebot2 (>=2.2.0,<3.0.0)
Requires-Dist: openai (>=1.0.0,<2.0.0)
Requires-Dist: silk-python (>=0.2.6,<0.3.0)
Project-URL: Repository, https://github.com/captain-wangrun-cn/nonebot-plugin-aitalk
